tubox_client/__init__.py
tubox_client/api_client.py
tubox_client/api_protocol.py
tubox_client/client_session.py
tubox_client/config.py
tubox_client/connection_pool.py
tubox_client/exceptions.py
tubox_client/transaction_errors.py
tubox_client/transactions.py
tubox_client-1.0.0.dist-info/licenses/LICENSE
tubox_client-1.0.0.dist-info/METADATA
tubox_client-1.0.0.dist-info/WHEEL
tubox_client-1.0.0.dist-info/top_level.txt
tubox_client-1.0.0.dist-info/RECORD
