Metadata-Version: 2.4
Name: tubox-client
Version: 1.0.0
Summary: Official Python client for Tubox Database
Home-page: https://tubox.cloud
Author: Tubox
Author-email: aegis.invincible@gmail.com
License: MIT
Project-URL: Documentation, https://tubox.cloud/
Project-URL: Source, https://github.com/axiomchronicles/tubox-client
Project-URL: Tracker, https://github.com/axiomchronicles/tubox-client/issues
Keywords: tubox database async client driver
Classifier: Development Status :: 5 - Production/Stable
Classifier: Intended Audience :: Developers
Classifier: License :: OSI Approved :: MIT License
Classifier: Programming Language :: Python :: 3
Classifier: Programming Language :: Python :: 3.8
Classifier: Programming Language :: Python :: 3.9
Classifier: Programming Language :: Python :: 3.10
Classifier: Programming Language :: Python :: 3.11
Classifier: Topic :: Database
Classifier: Topic :: Software Development :: Libraries :: Python Modules
Classifier: Framework :: AsyncIO
Requires-Python: >=3.8
License-File: LICENSE
Requires-Dist: crous>=1.0.0
Dynamic: author
Dynamic: author-email
Dynamic: classifier
Dynamic: description
Dynamic: description-content-type
Dynamic: home-page
Dynamic: keywords
Dynamic: license
Dynamic: license-file
Dynamic: project-url
Dynamic: requires-dist
Dynamic: requires-python
Dynamic: summary
